tinicly/__init__.py
tinicly/__main__.py
tinicly-0.1.4.dist-info/METADATA
tinicly-0.1.4.dist-info/WHEEL
tinicly-0.1.4.dist-info/entry_points.txt
tinicly-0.1.4.dist-info/licenses/LICENSE
tinicly-0.1.4.dist-info/RECORD
